evalkit_api_client/__init__.py
evalkit_api_client/errors.py
evalkit_api_client/interface.py
evalkit_api_client/types.py
evalkit_api_client/v1_client.py
evalkit_api_client-0.0.1a1.dist-info/METADATA
evalkit_api_client-0.0.1a1.dist-info/RECORD
evalkit_api_client-0.0.1a1.dist-info/WHEEL
evalkit_api_client-0.0.1a1.dist-info/dependency_links.txt
evalkit_api_client-0.0.1a1.dist-info/top_level.txt
