Metadata-Version: 2.1
Name: evalkit-api-client
Version: 0.0.1a1
Summary: This is a library for making requests to a EvaluationKIT API.
Home-page: https://github.com/lcary/canvas-lms-tools
Author: Kyle Lawlor
Author-email: klawlor419@gmail.com
License: Apache
Download-URL: https://github.com/lcary/canvas-lms-tools/archive/0.0.1a1
Platform: UNKNOWN
Classifier: Development Status :: 3 - Alpha
Classifier: Intended Audience :: Developers
Classifier: Programming Language :: Python :: 3
Requires-Dist: requests (==2.19.1)
